LICENSE
MANIFEST.in
README.rst
VERSION
requirements.txt
setup.py
src/kser_operation/__init__.py
src/kser_operation/operation.py
src/kser_operation/registry.py
src/kser_operation/task.py
src/kser_operation.egg-info/PKG-INFO
src/kser_operation.egg-info/SOURCES.txt
src/kser_operation.egg-info/dependency_links.txt
src/kser_operation.egg-info/entry_points.txt
src/kser_operation.egg-info/requires.txt
src/kser_operation.egg-info/top_level.txt
src/kser_operation.egg-info/zip-safe