Metadata-Version: 1.1
Name: kser-operation
Version: 0.0.15
Summary: Operation serializer for Kser
Home-page: https://github.com/cdumay/kser-operation
Author: Cedric DUMAY
Author-email: cedric.dumay@gmail.com
License: MIT
Platform: UNKNOWN
Classifier: Programming Language :: Python
